simplex/__init__.py
simplex/simplex.py
simplex_api-0.0.3.dist-info/LICENSE
simplex_api-0.0.3.dist-info/METADATA
simplex_api-0.0.3.dist-info/WHEEL
simplex_api-0.0.3.dist-info/top_level.txt
simplex_api-0.0.3.dist-info/RECORD
