Metadata-Version: 2.1
Name: simplex-api
Version: 0.0.3
Summary: Simplex core api for managing simulations.
Author-email: Marco Nocito <mnocito@mit.edu>
Project-URL: Homepage, https://github.com/mnocito/simplex-api
Classifier: Programming Language :: Python :: 3
Classifier: License :: OSI Approved :: MIT License
Classifier: Operating System :: OS Independent
Requires-Python: >=3.7
License-File: LICENSE
Requires-Dist: numpy >=1.25.2
Requires-Dist: requests >=2.26.0
